[{"__symbolic":"module","version":4,"metadata":{"ɵ0":{"__symbolic":"error","message":"Lambda not supported","line":7,"character":13},"ThyCheckboxComponent":{"__symbolic":"class","extends":{"__symbolic":"reference","module":"../shared","name":"ThyFormCheckBaseComponent","line":21,"character":42},"decorators":[{"__symbolic":"call","expression":{"__symbolic":"reference","module":"@angular/core","name":"Component","line":10,"character":1},"arguments":[{"selector":"[thy-checkbox],[thyCheckbox]","template":"<input class=\"form-check-input\" [checked]=\"_innerValue\" (change)=\"change()\" type=\"checkbox\" [disabled]=\"_disabled\"> <span class=\"form-check-label\">{{_labelText}}</span> <ng-content></ng-content>","providers":[{"provide":{"__symbolic":"reference","module":"@angular/forms","name":"NG_VALUE_ACCESSOR","line":15,"character":21},"useExisting":{"__symbolic":"reference","name":"ThyCheckboxComponent"},"multi":true}]}]}],"members":{"__ctor__":[{"__symbolic":"constructor","parameters":[{"__symbolic":"reference","module":"../shared","name":"ThyTranslate","line":23,"character":22}]}]}}}}]