[{"__symbolic":"module","version":4,"metadata":{"InputSize":{"__symbolic":"interface"},"SelectMode":{"__symbolic":"interface"},"ThyCustomSelectTriggerType":{"__symbolic":"interface"},"OptionValue":{"__symbolic":"interface"},"ɵ0":{"__symbolic":"error","message":"Lambda not supported","line":54,"character":13},"ThySelectCustomComponent":{"__symbolic":"class","decorators":[{"__symbolic":"call","expression":{"__symbolic":"reference","module":"@angular/core","name":"Component","line":56,"character":1},"arguments":[{"selector":"thy-custom-select","template":"<div cdk-overlay-origin (click)=\"toggle()\" #origin=\"cdkOverlayOrigin\" #trigger class=\"form-control form-control-custom\" [class.disabled]=\"_disabled\" [class.thy-select-selection]=\"!thyMode\" [ngClass]=\"_size ? 'form-control-' + _size : ''\" > <ng-container [ngSwitch]=\"empty\"> <span class=\"text-placeholder d-inline-block\" *ngSwitchCase=\"true\"> {{ thyPlaceHolder }} </span> <ng-container *ngSwitchCase=\"false\" [ngSwitch]=\"!!selectedValueDisplayRef\"> <ng-container *ngSwitchCase=\"true\"> <ng-container *ngTemplateOutlet=\"selectedValueDisplayRef; context: selectedDisplayContext\"></ng-container> </ng-container> <ng-container *ngSwitchDefault [ngSwitch]=\"thyMode\"> <ng-container *ngSwitchCase=\"'multiple'\"> <span class=\"mr-1\" *ngFor=\"let item of selected; index as i\" thyLabel=\"default\" thyAfterIcon=\"wtf-times\" (click)=\"remove(item, $event)\" > {{ item.thyLabelText }} </span> </ng-container> <ng-container *ngSwitchDefault> <span>{{ firstSelected.thyLabelText }}</span> </ng-container> </ng-container> <a class=\"thy-select-remove remove-link\" href=\"javascript:;\" (click)=\"clearSelectValue($event)\" *ngIf=\"thyAllowClear\" > <i class=\"wtf wtf-times-circle\"></i> </a> </ng-container> </ng-container> </div> <ng-template cdk-connected-overlay cdkConnectedOverlayLockPosition cdkConnectedOverlayHasBackdrop [cdkConnectedOverlayPositions]=\"positions\" cdkConnectedOverlayBackdropClass=\"cdk-overlay-transparent-backdrop\" [cdkConnectedOverlayOrigin]=\"origin\" [cdkConnectedOverlayOpen]=\"panelOpen\" [cdkConnectedOverlayWidth]=\"triggerRect?.width\" (backdropClick)=\"close()\" (detach)=\"close()\" > <div class=\"thy-select-container\" (mouseleave)=\"onSelectContainerMouseleave($event)\"> <div class=\"trgger-top-leave-block\"></div> <div class=\"trgger-bottom-leave-block\"></div> <div class=\"thy-select-search\" *ngIf=\"thyShowSearch\"> <thy-input-search thyAutofocus name=\"search\" [(ngModel)]=\"searchText\" (ngModelChange)=\"onSearchFilter()\" ></thy-input-search> </div> <ng-container *ngIf=\"options.length > 0 || optionGroups.length > 0; else emptyPlaceholder\"> <div class=\"thy-select-custom-options\"> <ng-content></ng-content> </div> </ng-container> <ng-template #emptyPlaceholder> <div class=\"pl-4 pt-1 pb-1 text-placeholder\">{{ _emptyStateText }}</div> </ng-template> </div> </ng-template> ","exportAs":"thyCustomSelect","providers":[{"provide":{"__symbolic":"reference","module":"./option.component","name":"THY_SELECT_OPTION_PARENT_COMPONENT","line":62,"character":21},"useExisting":{"__symbolic":"reference","name":"ThySelectCustomComponent"}},{"provide":{"__symbolic":"reference","module":"@angular/forms","name":"NG_VALUE_ACCESSOR","line":66,"character":21},"useExisting":{"__symbolic":"reference","name":"ThySelectCustomComponent"},"multi":true},{"__symbolic":"reference","module":"../shared/update-host-class.service","name":"UpdateHostClassService","line":70,"character":8}],"changeDetection":{"__symbolic":"select","expression":{"__symbolic":"reference","module":"@angular/core","name":"ChangeDetectionStrategy","line":72,"character":21},"member":"OnPush"}}]}],"members":{"_isSelectCustom":[{"__symbolic":"property","decorators":[{"__symbolic":"call","expression":{"__symbolic":"reference","module":"@angular/core","name":"HostBinding","line":112,"character":5},"arguments":["class.thy-select-custom"]}]}],"_isSelect":[{"__symbolic":"property","decorators":[{"__symbolic":"call","expression":{"__symbolic":"reference","module":"@angular/core","name":"HostBinding","line":114,"character":5},"arguments":["class.thy-select"]}]}],"panelOpen":[{"__symbolic":"property","decorators":[{"__symbolic":"call","expression":{"__symbolic":"reference","module":"@angular/core","name":"HostBinding","line":119,"character":5},"arguments":["class.menu-is-opened"]}]}],"thyOnSearch":[{"__symbolic":"property","decorators":[{"__symbolic":"call","expression":{"__symbolic":"reference","module":"@angular/core","name":"Output","line":124,"character":5}}]}],"thyShowSearch":[{"__symbolic":"property","decorators":[{"__symbolic":"call","expression":{"__symbolic":"reference","module":"@angular/core","name":"Input","line":126,"character":5}}]}],"thyPlaceHolder":[{"__symbolic":"property","decorators":[{"__symbolic":"call","expression":{"__symbolic":"reference","module":"@angular/core","name":"Input","line":128,"character":5}}]}],"thyServerSearch":[{"__symbolic":"property","decorators":[{"__symbolic":"call","expression":{"__symbolic":"reference","module":"@angular/core","name":"Input","line":130,"character":5}}]}],"thyHoverTriggerAction":[{"__symbolic":"property","decorators":[{"__symbolic":"call","expression":{"__symbolic":"reference","module":"@angular/core","name":"Input","line":132,"character":5}}]}],"thyMode":[{"__symbolic":"property","decorators":[{"__symbolic":"call","expression":{"__symbolic":"reference","module":"@angular/core","name":"Input","line":134,"character":5}}]}],"thySize":[{"__symbolic":"property","decorators":[{"__symbolic":"call","expression":{"__symbolic":"reference","module":"@angular/core","name":"Input","line":143,"character":5}}]}],"thyEmptyStateText":[{"__symbolic":"property","decorators":[{"__symbolic":"call","expression":{"__symbolic":"reference","module":"@angular/core","name":"Input","line":148,"character":5}}]}],"thyAllowClear":[{"__symbolic":"property","decorators":[{"__symbolic":"call","expression":{"__symbolic":"reference","module":"@angular/core","name":"Input","line":153,"character":5}}]}],"thyLoadingDone":[{"__symbolic":"property","decorators":[{"__symbolic":"call","expression":{"__symbolic":"reference","module":"@angular/core","name":"Input","line":155,"character":5}}]}],"thyDisabled":[{"__symbolic":"property","decorators":[{"__symbolic":"call","expression":{"__symbolic":"reference","module":"@angular/core","name":"Input","line":160,"character":5}}]}],"selectedValueDisplayRef":[{"__symbolic":"property","decorators":[{"__symbolic":"call","expression":{"__symbolic":"reference","module":"@angular/core","name":"ContentChild","line":209,"character":5},"arguments":["selectedDisplay"]}]}],"trigger":[{"__symbolic":"property","decorators":[{"__symbolic":"call","expression":{"__symbolic":"reference","module":"@angular/core","name":"ViewChild","line":211,"character":5},"arguments":["trigger"]}]}],"options":[{"__symbolic":"property","decorators":[{"__symbolic":"call","expression":{"__symbolic":"reference","module":"@angular/core","name":"ContentChildren","line":213,"character":5},"arguments":[{"__symbolic":"reference","module":"./option.component","name":"ThyOptionComponent","line":213,"character":21},{"descendants":true}]}]}],"optionGroups":[{"__symbolic":"property","decorators":[{"__symbolic":"call","expression":{"__symbolic":"reference","module":"@angular/core","name":"ContentChildren","line":215,"character":5},"arguments":[{"__symbolic":"reference","module":"./option-group.component","name":"ThySelectOptionGroupComponent","line":215,"character":21}]}]}],"__ctor__":[{"__symbolic":"constructor","parameters":[{"__symbolic":"reference","module":"@angular/core","name":"NgZone","line":218,"character":25},{"__symbolic":"reference","module":"@angular/core","name":"ElementRef","line":219,"character":28},{"__symbolic":"reference","module":"../shared/update-host-class.service","name":"UpdateHostClassService","line":220,"character":40},{"__symbolic":"reference","module":"@angular/core","name":"Renderer2","line":221,"character":26},{"__symbolic":"reference","module":"@angular/cdk/overlay","name":"Overlay","line":222,"character":25},{"__symbolic":"reference","module":"@angular/cdk/overlay","name":"ViewportRuler","line":223,"character":31},{"__symbolic":"reference","module":"@angular/core","name":"ChangeDetectorRef","line":224,"character":35}]}],"trggleHover":[{"__symbolic":"method","decorators":[{"__symbolic":"call","expression":{"__symbolic":"reference","module":"@angular/core","name":"HostListener","line":229,"character":5},"arguments":["mouseover",["$event"]]}]}],"onSelectContainerMouseleave":[{"__symbolic":"method"}],"writeValue":[{"__symbolic":"method"}],"ngOnInit":[{"__symbolic":"method"}],"ngAfterContentInit":[{"__symbolic":"method"}],"_resetOptions":[{"__symbolic":"method"}],"_initializeSelection":[{"__symbolic":"method"}],"_setSelecttionByModelValue":[{"__symbolic":"method"}],"registerOnChange":[{"__symbolic":"method"}],"registerOnTouched":[{"__symbolic":"method"}],"_emitModelValueChange":[{"__symbolic":"method"}],"remove":[{"__symbolic":"method"}],"clearSelectValue":[{"__symbolic":"method"}],"toggle":[{"__symbolic":"method"}],"open":[{"__symbolic":"method"}],"close":[{"__symbolic":"method"}],"onSearchFilter":[{"__symbolic":"method"}],"_instanceSelectionModel":[{"__symbolic":"method"}],"_onSelect":[{"__symbolic":"method"}],"ngOnDestroy":[{"__symbolic":"method"}]}}}}]